Metadata-Version: 2.1
Name: cmake-setuptools
Version: 0.1.2
Summary: Provides some usable cmake related build extensions
Home-page: https://github.com/raydouglass/cmake_setuptools
Author: Ray Douglass
License: Apache 2.0
Platform: UNKNOWN
Classifier: Intended Audience :: Developers
Classifier: License :: OSI Approved :: Apache Software License
Classifier: Operating System :: POSIX :: Linux
Classifier: Programming Language :: Python :: 3
Classifier: Topic :: Software Development :: Build Tools
